gridlines/__init__.py
gridlines/interactive.py
gridlines/print_table.py
gridlines/table.py
gridlines-1.0.0.dist-info/licenses/LICENSE
gridlines-1.0.0.dist-info/METADATA
gridlines-1.0.0.dist-info/WHEEL
gridlines-1.0.0.dist-info/top_level.txt
gridlines-1.0.0.dist-info/RECORD
