Metadata-Version: 2.4
Name: gridlines
Version: 1.0.0
Summary: Package for creating, using and showing tables in the Terminal, even interactive ones
Author-email: Matze Murek <matze.murek@gmail.com>
License: Apache-2.0
Project-URL: Homepage, https://github.com/M-Mrk/Gridlines
Project-URL: Repository, https://github.com/M-Mrk/Gridlines
Project-URL: Issues, https://github.com/M-Mrk/Gridlines/issues
Keywords: table,TUI,terminal,gridlines
Classifier: Programming Language :: Python :: 3
Classifier: License :: OSI Approved :: Apache Software License
Classifier: Operating System :: OS Independent
Requires-Python: >=3.8
License-File: LICENSE
Requires-Dist: rich>=13.0.0
Requires-Dist: readchar>=4.0.0
Dynamic: license-file
